concat_video_g4/__init__.py
concat_video_g4-1.0.0.dist-info/LICENSE
concat_video_g4-1.0.0.dist-info/METADATA
concat_video_g4-1.0.0.dist-info/WHEEL
concat_video_g4-1.0.0.dist-info/top_level.txt
concat_video_g4-1.0.0.dist-info/RECORD
